{
  "metadata": {
    "_stopper_comment": "While the original config had 500, early stopping will now switch it to 150",
    "_stopper_kwargs_removed_comment": "stopper_kwargs config removed after HPO: {'frequency': 50, 'patience': 2, 'relative_delta': 0.002}",
    "best_trial_evaluation": 0.4169646921126211,
    "best_trial_number": 53,
    "git_hash": "UNHASHED",
    "version": "1.10.1"
  },
  "pipeline": {
    "evaluation_kwargs": {
      "batch_size": null
    },
    "evaluator": "rankbased",
    "evaluator_kwargs": {
      "filtered": true
    },
    "filter_validation_when_testing": true,
    "loss": "crossentropy",
    "model": "transe",
    "model_kwargs": {
      "embedding_dim": 32,
      "scoring_fct_norm": 2
    },
    "optimizer": "adam",
    "optimizer_kwargs": {
      "lr": 0.0010109935195690058,
      "weight_decay": 0.0
    },
    "regularizer": "no",
    "testing": "<user defined>",
    "training": "<user defined>",
    "training_kwargs": {
      "batch_size": 256,
      "label_smoothing": 0.7,
      "num_epochs": 150
    },
    "training_loop": "lcwa",
    "validation": "<user defined>"
  }
}